mopidy_rpi_remote/__init__.py
mopidy_rpi_remote/__main__.py
mopidy_rpi_remote/cli.py
mopidy_rpi_remote/config.py
mopidy_rpi_remote/control.py
mopidy_rpi_remote/display.py
mopidy_rpi_remote/mqtt.py
mopidy_rpi_remote/fonts/ProggyTiny.ttf
mopidy_rpi_remote/fonts/pixelmix.ttf
mopidy_rpi_remote-0.1.0.dist-info/LICENSE
mopidy_rpi_remote-0.1.0.dist-info/METADATA
mopidy_rpi_remote-0.1.0.dist-info/WHEEL
mopidy_rpi_remote-0.1.0.dist-info/entry_points.txt
mopidy_rpi_remote-0.1.0.dist-info/top_level.txt
mopidy_rpi_remote-0.1.0.dist-info/RECORD
