Metadata-Version: 2.1
Name: mopidy-rpi-remote
Version: 0.1.0
Summary: Remote controller for Mopidy running on Raspberry Pi Zero W
Home-page: https://github.com/odiroot/mopidy-hw-remote
Author: Michal Odnous
Author-email: odiroot@users.noreply.github.com
License: Apache
Platform: UNKNOWN
Classifier: Development Status :: 4 - Beta
Classifier: Environment :: Console
Classifier: Intended Audience :: Developers
Classifier: License :: OSI Approved :: Apache Software License
Classifier: Operating System :: Unix
Classifier: Natural Language :: English
Classifier: Programming Language :: Python :: 3
Classifier: Programming Language :: Python :: 3.6
Classifier: Programming Language :: Python :: Implementation :: CPython
Classifier: Topic :: Multimedia
Classifier: Topic :: Utilities
Requires-Python: >=3.5
Requires-Dist: luma.oled (~=3.3.0)
Requires-Dist: paho-mqtt (~=1.4.0)
